{
  "id": "skilltree:alchemist_47",
  "bonuses": [
    {
      "type": "skilltree:healing",
      "chance": 1.0,
      "amount": 1.0,
      "event_listener": {
        "item_condition": {
          "potion_type": "any",
          "type": "skilltree:potion"
        },
        "player_condition": {
          "type": "skilltree:none"
        },
        "player_multiplier": {
          "type": "skilltree:none"
        },
        "type": "skilltree:item_used"
      }
    }
  ],
  "requirements": [],
  "directConnections": [
    "skilltree:alchemist_33"
  ],
  "longConnections": [],
  "oneWayConnections": [],
  "tags": [],
  "backgroundTexture": "skilltree:textures/icons/background/lesser.png",
  "iconTexture": "skilltree:textures/icons/potion_red.png",
  "borderTexture": "skilltree:textures/tooltip/lesser.png",
  "positionX": -93.52729,
  "positionY": 89.998,
  "buttonSize": 16,
  "isStartingPoint": false
}