{
  "id": "skilltree:alchemist_25",
  "bonuses": [
    {
      "type": "skilltree:inflict_effect",
      "chance": 0.02,
      "max_stacks": 0,
      "effect": "minecraft:slowness",
      "duration": 100,
      "amplifier": 0,
      "event_listener": {
        "damage_condition": {
          "type": "skilltree:none"
        },
        "enemy_condition": {
          "type": "skilltree:none"
        },
        "player_condition": {
          "type": "skilltree:none"
        },
        "enemy_multiplier": {
          "type": "skilltree:none"
        },
        "player_multiplier": {
          "type": "skilltree:none"
        },
        "target": "enemy",
        "type": "skilltree:attack"
      }
    }
  ],
  "requirements": [],
  "directConnections": [
    "skilltree:alchemist_22"
  ],
  "longConnections": [],
  "oneWayConnections": [],
  "tags": [],
  "backgroundTexture": "skilltree:textures/icons/background/lesser.png",
  "iconTexture": "skilltree:textures/icons/potion_gray_small.png",
  "borderTexture": "skilltree:textures/tooltip/lesser.png",
  "positionX": 62.353252,
  "positionY": 72.00199,
  "buttonSize": 16,
  "isStartingPoint": false
}